{
    "source_id": 49000226,
    "validate_csv_fields":{
        "product_id":{
                    "source_id":          {"required": true},
                    "source_internal_id": {"required": true},
                    "ProductName":        {"required": true},
                    "ID_kind":            {"required": true},
                    "ID_value":           {"required": true}
        },
        "product":{
                    "source_id":            {"required": true},
                    "source_internal_id":   {"required": true},
                    "ProductName":          {"required": true},
                    "OriginalCategoryName": {"required": true},
                    "PicURL":               {"required": true},
                    "ProductManufacturer":  {"required": false},
                    "TestUrl":              {"required": true}
        }
        
    }
}
